Metadata-Version: 2.1
Name: truconsts
Version: 0.0.9
Summary: Simple, easy to use with intuitive APIs, for managing constants in your Python applications.
Author-email: Jim Chng <jimchng@outlook.com>
Keywords: truconsts,truly constants,constants
Classifier: Development Status :: 3 - Alpha
Classifier: License :: OSI Approved :: MIT License
Classifier: Programming Language :: Python :: 3.8
Classifier: Programming Language :: Python :: 3.9
Classifier: Programming Language :: Python :: 3.10
Classifier: Programming Language :: Python :: 3.11
Classifier: Environment :: Web Environment
Classifier: Operating System :: OS Independent
Classifier: Framework :: AsyncIO
Requires-Python: >=3.8
License-File: LICENSE
